__init__.py
gsnapshot.py
gsnapshot-0.0.2.dist-info/METADATA
gsnapshot-0.0.2.dist-info/WHEEL
gsnapshot-0.0.2.dist-info/top_level.txt
gsnapshot-0.0.2.dist-info/RECORD
