Metadata-Version: 2.2
Name: gsnapshot
Version: 0.0.2
Summary: a package for automatic repo snapshot using git
Author-email: Mingkun Bao <bravomikekilo@outlook.com>
License: MIT
Classifier: Programming Language :: Python :: 3
Requires-Python: >=3.8
Requires-Dist: filelock
